spikes/CONFIGS.py
spikes/DATA.py
spikes/__init__.py
spikes/normalize.py
spikes/print_spike.py
spikes/spike.py
spikes/spike_data.py
spikes-0.1.0b0.dist-info/DESCRIPTION.rst
spikes-0.1.0b0.dist-info/METADATA
spikes-0.1.0b0.dist-info/RECORD
spikes-0.1.0b0.dist-info/WHEEL
spikes-0.1.0b0.dist-info/entry_points.txt
spikes-0.1.0b0.dist-info/metadata.json
spikes-0.1.0b0.dist-info/top_level.txt
